deepwiki/__init__.py
deepwiki/cli.py
deepwiki/client.py
ask_deepwiki-0.1.0.dist-info/METADATA
ask_deepwiki-0.1.0.dist-info/WHEEL
ask_deepwiki-0.1.0.dist-info/entry_points.txt
ask_deepwiki-0.1.0.dist-info/RECORD
