Metadata-Version: 2.4
Name: ask-deepwiki
Version: 0.1.0
Summary: CLI tool for querying DeepWiki documentation
Project-URL: Homepage, https://github.com/4rays/deepwiki-cli
Project-URL: Repository, https://github.com/4rays/deepwiki-cli
Project-URL: Issues, https://github.com/4rays/deepwiki-cli/issues
Author: DeepWiki CLI
License: MIT
Keywords: cli,deepwiki,documentation,mcp
Classifier: Development Status :: 4 - Beta
Classifier: Environment :: Console
Classifier: Intended Audience :: Developers
Classifier: License :: OSI Approved :: MIT License
Classifier: Programming Language :: Python :: 3
Classifier: Programming Language :: Python :: 3.10
Classifier: Programming Language :: Python :: 3.11
Classifier: Programming Language :: Python :: 3.12
Classifier: Programming Language :: Python :: 3.13
Classifier: Topic :: Documentation
Classifier: Topic :: Software Development :: Documentation
Requires-Python: >=3.10
Requires-Dist: click>=8.0.0
Requires-Dist: httpx>=0.27.0
Requires-Dist: mcp>=1.0.0
